README.md
livelock_server.py
setup.py
livelock/__init__.py
livelock/_compat.py
livelock/client.py
livelock/connection.py
livelock/memory_storage.py
livelock/server.py
livelock/shared.py
livelock/stats.py
livelock/storage.py
livelock/tcp_info.py
livelock/tcp_opts.py
livelock/tcp_utils.py
livelock.egg-info/PKG-INFO
livelock.egg-info/SOURCES.txt
livelock.egg-info/dependency_links.txt
livelock.egg-info/top_level.txt