Metadata-Version: 1.1
Name: livelock
Version: 0.7.6
Summary: Distributed lock server without ttl and client processes death detection
Home-page: UNKNOWN
Author: Artem Sovetnikov
Author-email: asovetnikov@gmail.com
License: UNKNOWN
Platform: Any
Classifier: Development Status :: 4 - Beta
Classifier: Intended Audience :: Developers
Classifier: Operating System :: OS Independent
Classifier: Programming Language :: Python
